{
  "parent": "lgp:advancement/guide_part2/get_shield",
  "criteria": {
    "fishing_rod": {
      "conditions": {
        "items": [
          {
            "items": [
              "minecraft:fishing_rod"
            ]
          }
        ]
      },
      "trigger": "minecraft:inventory_changed"
    }
  },
  "display": {
    "announce_to_chat": true,
    "description": "用铜块或铁块、三根木棍和两条线制作一把钓鱼竿",
    "frame": "task",
    "hidden": false,
    "icon": {
      "item": "minecraft:fishing_rod"
    },
    "show_toast": true,
    "title": "盲盒游戏"
  },
  "requirements": [
    [
      "fishing_rod"
    ]
  ]
}